satio_pc/__init__.py
satio_pc/_version.py
satio_pc/azure.py
satio_pc/cli.py
satio_pc/errors.py
satio_pc/extension.py
satio_pc/extraction.py
satio_pc/features.py
satio_pc/geotiff.py
satio_pc/grid.py
satio_pc/reader.py
satio_pc/sentinel1.py
satio_pc/sentinel2.py
satio_pc/change/__init__.py
satio_pc/indices/__init__.py
satio_pc/indices/_alt.py
satio_pc/indices/biopar/__init__.py
satio_pc/indices/biopar/config.py
satio_pc/layers/__init__.py
satio_pc/layers/ne_countries_simple.fgb
satio_pc/layers/ne_landsea_simple.fgb
satio_pc/layers/s2grid_all_bounds.fgb
satio_pc/layers/s2grid_bounds.fgb
satio_pc/layers/sentinel2_jp2_windows.json
satio_pc/preprocessing/__init__.py
satio_pc/preprocessing/clouds.py
satio_pc/preprocessing/composite.py
satio_pc/preprocessing/coregistration.py
satio_pc/preprocessing/interpolate.py
satio_pc/preprocessing/pearson.py
satio_pc/preprocessing/rescale.py
satio_pc/preprocessing/speckle.py
satio_pc/preprocessing/timer.py
satio_pc/superres/__init__.py
satio_pc/superres/cv.py
satio_pc/superres/improphe.py
satio_pc/superres/super_image.py
satio_pc-0.0.14.dist-info/METADATA
satio_pc-0.0.14.dist-info/WHEEL
satio_pc-0.0.14.dist-info/licenses/LICENSE
satio_pc-0.0.14.dist-info/RECORD
